[
	{
		"id": 228525,
		"name": "Bookshelf",
		"authors": [
			{
				"name": "DarkhaxDev",
				"url": "https://www.curseforge.com/members/6968547-darkhaxdev?username=darkhaxdev",
				"projectId": 228525,
				"id": 30959,
				"projectTitleId": null,
				"projectTitleTitle": null,
				"userId": 6968547,
				"twitchId": 138092450
			}
		],
		"attachments": [
			{
				"id": 15169,
				"projectId": 228525,
				"description": "",
				"isDefault": false,
				"thumbnailUrl": "https://media.forgecdn.net/avatars/thumbnails/15/169/256/256/635617078813942671.png",
				"title": "635617078813942671.png",
				"url": "https://media.forgecdn.net/avatars/15/169/635617078813942671.png",
				"status": 1
			}, {
				"id": 197186,
				"projectId": 228525,
				"description": "",
				"isDefault": true,
				"thumbnailUrl": "https://media.forgecdn.net/avatars/thumbnails/197/186/256/256/636890440894617244.png",
				"title": "636890440894617244.png",
				"url": "https://media.forgecdn.net/avatars/197/186/636890440894617244.png",
				"status": 1
			}, {
				"id": 356665,
				"projectId": 228525,
				"description": "This is a debug command added by Bookshelf. You can use it to export game data of the held item in many different formats. For example the ingredient option will give you a JSON string that can be used in datapacks for things like recipe inputs.",
				"isDefault": false,
				"thumbnailUrl": "https://media.forgecdn.net/attachments/thumbnails/356/665/310/172/hand_command.png",
				"title": "Command: /bookshelf hand",
				"url": "https://media.forgecdn.net/attachments/356/665/hand_command.png",
				"status": 1
			}
		],
		"issueTrackerUrl": "https://github.com/Darkhax-Minecraft/Bookshelf/issues",
		"wikiUrl": "",
		"sourceUrl": "https://github.com/Darkhax-Minecraft/Bookshelf",
		"websiteUrl": "https://www.curseforge.com/minecraft/mc-mods/bookshelf",
		"gameId": 432,
		"summary": "An open source library for other mods!",
		"defaultFileId": 3604213,
		"downloadCount": 86414728.0,
		"latestFiles": [
			{
				"id": 2723580,
				"displayName": "Bookshelf-1.12.2-2.3.584.jar",
				"fileName": "Bookshelf-1.12.2-2.3.584.jar",
				"fileDate": "2019-06-12T01:04:53.637Z",
				"fileLength": 266009,
				"releaseType": 1,
				"fileStatus": 4,
				"downloadUrl": "https://edge.forgecdn.net/files/2723/580/Bookshelf-1.12.2-2.3.584.jar",
				"isAlternate": false,
				"alternateFileId": 0,
				"dependencies": [],
				"isAvailable": true,
				"modules": [
					{
						"foldername": "META-INF",
						"fingerprint": 1695835537,
						"type": 3
					}, {
						"foldername": "assets",
						"fingerprint": 2075849057,
						"type": 3
					}, {
						"foldername": "mcmod.info",
						"fingerprint": 2905343425,
						"type": 3
					}, {
						"foldername": "net",
						"fingerprint": 2445593008,
						"type": 3
					}, {
						"foldername": "pack.mcmeta",
						"fingerprint": 4087128376,
						"type": 3
					}
				],
				"packageFingerprint": 244274784,
				"gameVersion": ["1.12.2"],
				"sortableGameVersion": [
					{
						"gameVersionPadded": "0000000001.0000000012.0000000002",
						"gameVersion": "1.12.2",
						"gameVersionReleaseDate": "2017-09-18T05:00:00Z",
						"gameVersionName": "1.12.2",
						"gameVersionTypeId": 628
					}
				],
				"installMetadata": null,
				"changelog": null,
				"hasInstallScript": false,
				"isCompatibleWithClient": true,
				"categorySectionPackageType": 6,
				"restrictProjectFileAccess": 1,
				"projectStatus": 4,
				"renderCacheId": 1574575,
				"fileLegacyMappingId": null,
				"projectId": 228525,
				"parentProjectFileId": null,
				"parentFileLegacyMappingId": null,
				"fileTypeId": null,
				"exposeAsAlternative": null,
				"packageFingerprintId": 323370593,
				"gameVersionDateReleased": "2008-03-01T06:00:00Z",
				"gameVersionMappingId": 1832435,
				"gameVersionId": 4458,
				"gameId": 432,
				"isServerPack": false,
				"serverPackFileId": null,
				"gameVersionFlavor": null,
				"hashes": [
					{
						"algorithm": 1,
						"value": "cf0d1ce4c6a0567a8275486bc56e250cec9ef692"
					}, {
						"algorithm": 2,
						"value": "cab65b9fe8dc2a851693341e8c65d0d3"
					}
				],
				"downloadCount": 180749
			}, {
				"id": 2758578,
				"displayName": "Bookshelf-1.14.4-4.2.35.jar",
				"fileName": "Bookshelf-1.14.4-4.2.35.jar",
				"fileDate": "2019-08-10T07:01:55.957Z",
				"fileLength": 92051,
				"releaseType": 2,
				"fileStatus": 4,
				"downloadUrl": "https://edge.forgecdn.net/files/2758/578/Bookshelf-1.14.4-4.2.35.jar",
				"isAlternate": false,
				"alternateFileId": 0,
				"dependencies": [],
				"isAvailable": true,
				"modules": [
					{
						"foldername": "META-INF",
						"fingerprint": 2521006806,
						"type": 3
					}, {
						"foldername": "assets",
						"fingerprint": 3535179281,
						"type": 3
					}, {
						"foldername": "logo.png",
						"fingerprint": 777571610,
						"type": 3
					}, {
						"foldername": "net",
						"fingerprint": 3039705890,
						"type": 3
					}, {
						"foldername": "pack.mcmeta",
						"fingerprint": 3022063081,
						"type": 3
					}
				],
				"packageFingerprint": 3459401766,
				"gameVersion": ["1.14.4"],
				"sortableGameVersion": [
					{
						"gameVersionPadded": "0000000001.0000000014.0000000004",
						"gameVersion": "1.14.4",
						"gameVersionReleaseDate": "2019-07-19T00:00:00Z",
						"gameVersionName": "1.14.4",
						"gameVersionTypeId": 64806
					}
				],
				"installMetadata": null,
				"changelog": null,
				"hasInstallScript": false,
				"isCompatibleWithClient": true,
				"categorySectionPackageType": 6,
				"restrictProjectFileAccess": 1,
				"projectStatus": 4,
				"renderCacheId": 1620161,
				"fileLegacyMappingId": null,
				"projectId": 228525,
				"parentProjectFileId": null,
				"parentFileLegacyMappingId": null,
				"fileTypeId": null,
				"exposeAsAlternative": null,
				"packageFingerprintId": 342667582,
				"gameVersionDateReleased": "2008-03-01T06:00:00Z",
				"gameVersionMappingId": 1890857,
				"gameVersionId": 4458,
				"gameId": 432,
				"isServerPack": false,
				"serverPackFileId": null,
				"gameVersionFlavor": null,
				"hashes": [
					{
						"algorithm": 1,
						"value": "907a13e347cf33f2498d26172d358b42d1227251"
					}, {
						"algorithm": 2,
						"value": "160202ee3ddc4ac1b88c64ebe1061dcd"
					}
				],
				"downloadCount": 9096
			}, {
				"id": 2808278,
				"displayName": "Bookshelf-1.14.4-4.2.51.jar",
				"fileName": "Bookshelf-1.14.4-4.2.51.jar",
				"fileDate": "2019-10-13T06:45:49.607Z",
				"fileLength": 113366,
				"releaseType": 3,
				"fileStatus": 4,
				"downloadUrl": "https://edge.forgecdn.net/files/2808/278/Bookshelf-1.14.4-4.2.51.jar",
				"isAlternate": false,
				"alternateFileId": 0,
				"dependencies": [],
				"isAvailable": true,
				"modules": [
					{
						"foldername": "META-INF",
						"fingerprint": 241629841,
						"type": 3
					}, {
						"foldername": "assets",
						"fingerprint": 714988807,
						"type": 3
					}, {
						"foldername": "logo.png",
						"fingerprint": 777571610,
						"type": 3
					}, {
						"foldername": "net",
						"fingerprint": 3887934935,
						"type": 3
					}, {
						"foldername": "pack.mcmeta",
						"fingerprint": 3022063081,
						"type": 3
					}
				],
				"packageFingerprint": 1510390343,
				"gameVersion": ["1.14.4"],
				"sortableGameVersion": [
					{
						"gameVersionPadded": "0000000001.0000000014.0000000004",
						"gameVersion": "1.14.4",
						"gameVersionReleaseDate": "2019-07-19T00:00:00Z",
						"gameVersionName": "1.14.4",
						"gameVersionTypeId": 64806
					}
				],
				"installMetadata": null,
				"changelog": null,
				"hasInstallScript": false,
				"isCompatibleWithClient": true,
				"categorySectionPackageType": 6,
				"restrictProjectFileAccess": 1,
				"projectStatus": 4,
				"renderCacheId": 1679776,
				"fileLegacyMappingId": null,
				"projectId": 228525,
				"parentProjectFileId": null,
				"parentFileLegacyMappingId": null,
				"fileTypeId": null,
				"exposeAsAlternative": null,
				"packageFingerprintId": 366681608,
				"gameVersionDateReleased": "2008-03-01T06:00:00Z",
				"gameVersionMappingId": 1969347,
				"gameVersionId": 4458,
				"gameId": 432,
				"isServerPack": false,
				"serverPackFileId": null,
				"gameVersionFlavor": null,
				"hashes": [
					{
						"algorithm": 1,
						"value": "05c8589abcf6ea136c897fe39b4fb32da0d0b26e"
					}, {
						"algorithm": 2,
						"value": "d72231d89ba0a65e33a96943e8b97f7b"
					}
				],
				"downloadCount": 2334
			}, {
				"id": 3000934,
				"displayName": "Bookshelf-1.16.1-6.0.2.jar",
				"fileName": "Bookshelf-1.16.1-6.0.2.jar",
				"fileDate": "2020-07-10T04:52:37.707Z",
				"fileLength": 131045,
				"releaseType": 2,
				"fileStatus": 4,
				"downloadUrl": "https://edge.forgecdn.net/files/3000/934/Bookshelf-1.16.1-6.0.2.jar",
				"isAlternate": false,
				"alternateFileId": 0,
				"dependencies": [],
				"isAvailable": true,
				"modules": [
					{
						"foldername": "META-INF",
						"fingerprint": 910968708,
						"type": 3
					}, {
						"foldername": "net",
						"fingerprint": 1007674970,
						"type": 3
					}, {
						"foldername": "pack.mcmeta",
						"fingerprint": 2119111672,
						"type": 3
					}, {
						"foldername": "assets",
						"fingerprint": 788307383,
						"type": 3
					}, {
						"foldername": "logo.png",
						"fingerprint": 777571610,
						"type": 3
					}
				],
				"packageFingerprint": 415059162,
				"gameVersion": ["1.16.1", "Forge"],
				"sortableGameVersion": [
					{
						"gameVersionPadded": "0000000001.0000000016.0000000001",
						"gameVersion": "1.16.1",
						"gameVersionReleaseDate": "2020-06-24T12:41:11.823Z",
						"gameVersionName": "1.16.1",
						"gameVersionTypeId": 70886
					}, {
						"gameVersionPadded": "0",
						"gameVersion": "",
						"gameVersionReleaseDate": "2019-08-01T00:00:00Z",
						"gameVersionName": "Forge",
						"gameVersionTypeId": 68441
					}
				],
				"installMetadata": null,
				"changelog": null,
				"hasInstallScript": false,
				"isCompatibleWithClient": true,
				"categorySectionPackageType": 6,
				"restrictProjectFileAccess": 1,
				"projectStatus": 4,
				"renderCacheId": 1918276,
				"fileLegacyMappingId": null,
				"projectId": 228525,
				"parentProjectFileId": null,
				"parentFileLegacyMappingId": null,
				"fileTypeId": null,
				"exposeAsAlternative": null,
				"packageFingerprintId": 485864186,
				"gameVersionDateReleased": "2008-03-01T06:00:00Z",
				"gameVersionMappingId": 2313315,
				"gameVersionId": 4458,
				"gameId": 432,
				"isServerPack": false,
				"serverPackFileId": null,
				"gameVersionFlavor": null,
				"hashes": [
					{
						"algorithm": 1,
						"value": "0b08a5b3dada0d1eb2b94c6d0afe4c77733df9f0"
					}, {
						"algorithm": 2,
						"value": "aa71e77beb78fe3984a205641150f681"
					}
				],
				"downloadCount": 6825
			}, {
				"id": 3604213,
				"displayName": "Bookshelf-Forge-1.16.5-10.4.31.jar",
				"fileName": "Bookshelf-Forge-1.16.5-10.4.31.jar",
				"fileDate": "2022-01-13T05:54:23.04Z",
				"fileLength": 316237,
				"releaseType": 1,
				"fileStatus": 4,
				"downloadUrl": "https://edge.forgecdn.net/files/3604/213/Bookshelf-Forge-1.16.5-10.4.31.jar",
				"isAlternate": false,
				"alternateFileId": 0,
				"dependencies": [],
				"isAvailable": true,
				"modules": [
					{
						"foldername": "META-INF",
						"fingerprint": 3411592648,
						"type": 3
					}, {
						"foldername": "assets",
						"fingerprint": 2504899875,
						"type": 3
					}, {
						"foldername": "mod_logo.png",
						"fingerprint": 777571610,
						"type": 3
					}, {
						"foldername": "net",
						"fingerprint": 573849751,
						"type": 3
					}, {
						"foldername": "pack.mcmeta",
						"fingerprint": 1432491059,
						"type": 3
					}
				],
				"packageFingerprint": 1175599866,
				"gameVersion": ["1.16.5", "Forge"],
				"sortableGameVersion": [
					{
						"gameVersionPadded": "0000000001.0000000016.0000000005",
						"gameVersion": "1.16.5",
						"gameVersionReleaseDate": "2021-01-15T14:14:48.91Z",
						"gameVersionName": "1.16.5",
						"gameVersionTypeId": 70886
					}, {
						"gameVersionPadded": "0",
						"gameVersion": "",
						"gameVersionReleaseDate": "2019-08-01T00:00:00Z",
						"gameVersionName": "Forge",
						"gameVersionTypeId": 68441
					}
				],
				"installMetadata": null,
				"changelog": null,
				"hasInstallScript": false,
				"isCompatibleWithClient": true,
				"categorySectionPackageType": 6,
				"restrictProjectFileAccess": 1,
				"projectStatus": 4,
				"renderCacheId": 2679406,
				"fileLegacyMappingId": null,
				"projectId": 228525,
				"parentProjectFileId": null,
				"parentFileLegacyMappingId": null,
				"fileTypeId": null,
				"exposeAsAlternative": null,
				"packageFingerprintId": 833439411,
				"gameVersionDateReleased": "2008-03-01T06:00:00Z",
				"gameVersionMappingId": 3666551,
				"gameVersionId": 4458,
				"gameId": 432,
				"isServerPack": false,
				"serverPackFileId": null,
				"gameVersionFlavor": null,
				"hashes": [
					{
						"algorithm": 1,
						"value": "61275b8088e9ec178d8bee51471bfa0a3b1c45ef"
					}, {
						"algorithm": 2,
						"value": "40daf0ad636c1ae6d954fc66c093c143"
					}
				],
				"downloadCount": 154500
			}, {
				"id": 3624195,
				"displayName": "Bookshelf-Fabric-1.18.1-12.0.3.jar",
				"fileName": "Bookshelf-Fabric-1.18.1-12.0.3.jar",
				"fileDate": "2022-01-26T10:26:02.103Z",
				"fileLength": 86992,
				"releaseType": 3,
				"fileStatus": 4,
				"downloadUrl": "https://edge.forgecdn.net/files/3624/195/Bookshelf-Fabric-1.18.1-12.0.3.jar",
				"isAlternate": false,
				"alternateFileId": 0,
				"dependencies": [],
				"isAvailable": true,
				"modules": [
					{
						"foldername": "META-INF",
						"fingerprint": 170449868,
						"type": 3
					}, {
						"foldername": "fabric.mod.json",
						"fingerprint": 3601106713,
						"type": 3
					}, {
						"foldername": "assets",
						"fingerprint": 619424013,
						"type": 3
					}, {
						"foldername": "bookshelf.mixins.json",
						"fingerprint": 478551572,
						"type": 3
					}, {
						"foldername": "pack.mcmeta",
						"fingerprint": 2024109781,
						"type": 3
					}, {
						"foldername": "Bookshelf-Fabric-1.18.1-refmap.json",
						"fingerprint": 1850167007,
						"type": 3
					}, {
						"foldername": "net",
						"fingerprint": 2832804115,
						"type": 3
					}
				],
				"packageFingerprint": 157917810,
				"gameVersion": ["1.18.1", "Fabric"],
				"sortableGameVersion": [
					{
						"gameVersionPadded": "0000000001.0000000018.0000000001",
						"gameVersion": "1.18.1",
						"gameVersionReleaseDate": "2021-12-10T10:37:38.06Z",
						"gameVersionName": "1.18.1",
						"gameVersionTypeId": 73250
					}, {
						"gameVersionPadded": "0",
						"gameVersion": "",
						"gameVersionReleaseDate": "2019-08-01T00:00:00Z",
						"gameVersionName": "Fabric",
						"gameVersionTypeId": 68441
					}
				],
				"installMetadata": null,
				"changelog": null,
				"hasInstallScript": false,
				"isCompatibleWithClient": true,
				"categorySectionPackageType": 6,
				"restrictProjectFileAccess": 1,
				"projectStatus": 4,
				"renderCacheId": 2704656,
				"fileLegacyMappingId": null,
				"projectId": 228525,
				"parentProjectFileId": null,
				"parentFileLegacyMappingId": null,
				"fileTypeId": null,
				"exposeAsAlternative": null,
				"packageFingerprintId": 844885518,
				"gameVersionDateReleased": "2019-08-01T00:00:00Z",
				"gameVersionMappingId": 3715089,
				"gameVersionId": 7499,
				"gameId": 432,
				"isServerPack": false,
				"serverPackFileId": null,
				"gameVersionFlavor": null,
				"hashes": [
					{
						"algorithm": 1,
						"value": "054667768a721b4673f702f4f1b93e6d90848943"
					}, {
						"algorithm": 2,
						"value": "a57aa01d69a26ea1c1c05ad373a69422"
					}
				],
				"downloadCount": 0
			}, {
				"id": 3624196,
				"displayName": "Bookshelf-Forge-1.18.1-12.0.3.jar",
				"fileName": "Bookshelf-Forge-1.18.1-12.0.3.jar",
				"fileDate": "2022-01-26T10:26:03.307Z",
				"fileLength": 91885,
				"releaseType": 3,
				"fileStatus": 4,
				"downloadUrl": "https://edge.forgecdn.net/files/3624/196/Bookshelf-Forge-1.18.1-12.0.3.jar",
				"isAlternate": false,
				"alternateFileId": 0,
				"dependencies": [],
				"isAvailable": true,
				"modules": [
					{
						"foldername": "META-INF",
						"fingerprint": 612602155,
						"type": 3
					}, {
						"foldername": "bookshelf.mixins.json",
						"fingerprint": 3455318323,
						"type": 3
					}, {
						"foldername": "bookshelf.refmap.json",
						"fingerprint": 22832208,
						"type": 3
					}, {
						"foldername": "logo.png",
						"fingerprint": 777571610,
						"type": 3
					}, {
						"foldername": "net",
						"fingerprint": 3328575432,
						"type": 3
					}, {
						"foldername": "pack.mcmeta",
						"fingerprint": 2024109781,
						"type": 3
					}
				],
				"packageFingerprint": 4199112067,
				"gameVersion": ["1.18.1", "Forge"],
				"sortableGameVersion": [
					{
						"gameVersionPadded": "0000000001.0000000018.0000000001",
						"gameVersion": "1.18.1",
						"gameVersionReleaseDate": "2021-12-10T10:37:38.06Z",
						"gameVersionName": "1.18.1",
						"gameVersionTypeId": 73250
					}, {
						"gameVersionPadded": "0",
						"gameVersion": "",
						"gameVersionReleaseDate": "2019-08-01T00:00:00Z",
						"gameVersionName": "Forge",
						"gameVersionTypeId": 68441
					}
				],
				"installMetadata": null,
				"changelog": null,
				"hasInstallScript": false,
				"isCompatibleWithClient": true,
				"categorySectionPackageType": 6,
				"restrictProjectFileAccess": 1,
				"projectStatus": 4,
				"renderCacheId": 2704657,
				"fileLegacyMappingId": null,
				"projectId": 228525,
				"parentProjectFileId": null,
				"parentFileLegacyMappingId": null,
				"fileTypeId": null,
				"exposeAsAlternative": null,
				"packageFingerprintId": 844885584,
				"gameVersionDateReleased": "2019-08-01T00:00:00Z",
				"gameVersionMappingId": 3715092,
				"gameVersionId": 7498,
				"gameId": 432,
				"isServerPack": false,
				"serverPackFileId": null,
				"gameVersionFlavor": null,
				"hashes": [
					{
						"algorithm": 1,
						"value": "9058262f5b92a6fab458f35840a16d667e892773"
					}, {
						"algorithm": 2,
						"value": "331361a799c5340be15d51f70d81e3f1"
					}
				],
				"downloadCount": 0
			}
		],
		"categories": [
			{
				"categoryId": 425,
				"name": "Miscellaneous",
				"url": "https://www.curseforge.com/minecraft/mc-mods/mc-miscellaneous",
				"avatarUrl": "https://media.forgecdn.net/avatars/6/40/635351497693711265.png",
				"parentId": 6,
				"rootId": 6,
				"projectId": 228525,
				"avatarId": 6040,
				"gameId": 432,
				"slug": "mc-miscellaneous",
				"dateModified": "2014-06-15T04:27:14.543Z"
			}, {
				"categoryId": 425,
				"name": "Miscellaneous",
				"url": "https://www.curseforge.com/minecraft/mc-mods/mc-miscellaneous",
				"avatarUrl": "https://media.forgecdn.net/avatars/6/40/635351497693711265.png",
				"parentId": 6,
				"rootId": 6,
				"projectId": 228525,
				"avatarId": 6040,
				"gameId": 432,
				"slug": "mc-miscellaneous",
				"dateModified": "2014-06-15T04:27:14.543Z"
			}, {
				"categoryId": 435,
				"name": "Server Utility",
				"url": "https://www.curseforge.com/minecraft/mc-mods/server-utility",
				"avatarUrl": "https://media.forgecdn.net/avatars/6/48/635351498950580836.png",
				"parentId": 6,
				"rootId": 6,
				"projectId": 228525,
				"avatarId": 6048,
				"gameId": 432,
				"slug": "server-utility",
				"dateModified": "2014-05-08T17:44:55.057Z"
			}, {
				"categoryId": 421,
				"name": "API and Library",
				"url": "https://www.curseforge.com/minecraft/mc-mods/library-api",
				"avatarUrl": "https://media.forgecdn.net/avatars/6/36/635351496947765531.png",
				"parentId": 6,
				"rootId": 6,
				"projectId": 228525,
				"avatarId": 6036,
				"gameId": 432,
				"slug": "library-api",
				"dateModified": "2014-05-23T03:21:44.06Z"
			}, {
				"categoryId": 421,
				"name": "API and Library",
				"url": "https://www.curseforge.com/minecraft/mc-mods/library-api",
				"avatarUrl": "https://media.forgecdn.net/avatars/6/36/635351496947765531.png",
				"parentId": 6,
				"rootId": 6,
				"projectId": 228525,
				"avatarId": 6036,
				"gameId": 432,
				"slug": "library-api",
				"dateModified": "2014-05-23T03:21:44.06Z"
			}
		],
		"status": 4,
		"primaryCategoryId": 425,
		"categorySection": {
			"id": 8,
			"gameId": 432,
			"name": "Mods",
			"packageType": 6,
			"path": "mods",
			"initialInclusionPattern": ".",
			"extraIncludePattern": null,
			"gameCategoryId": 6
		},
		"slug": "bookshelf",
		"gameVersionLatestFiles": [
			{
				"gameVersion": "1.18.1",
				"projectFileId": 3624196,
				"projectFileName": "Bookshelf-Forge-1.18.1-12.0.3.jar",
				"fileType": 3,
				"gameVersionFlavor": null,
				"gameVersionTypeId": 73250,
				"modLoader": 1
			}, {
				"gameVersion": "1.18.1",
				"projectFileId": 3624195,
				"projectFileName": "Bookshelf-Fabric-1.18.1-12.0.3.jar",
				"fileType": 3,
				"gameVersionFlavor": null,
				"gameVersionTypeId": 73250,
				"modLoader": 4
			}, {
				"gameVersion": "1.16.5",
				"projectFileId": 3604213,
				"projectFileName": "Bookshelf-Forge-1.16.5-10.4.31.jar",
				"fileType": 1,
				"gameVersionFlavor": null,
				"gameVersionTypeId": 70886,
				"modLoader": 1
			}, {
				"gameVersion": "1.16.5",
				"projectFileId": 3604210,
				"projectFileName": "Bookshelf-Forge-1.16.5-10.4.30.jar",
				"fileType": 3,
				"gameVersionFlavor": null,
				"gameVersionTypeId": 70886,
				"modLoader": 1
			}, {
				"gameVersion": "1.17.1",
				"projectFileId": 3596660,
				"projectFileName": "Bookshelf-Forge-1.17.1-11.0.3.jar",
				"fileType": 3,
				"gameVersionFlavor": null,
				"gameVersionTypeId": 73242,
				"modLoader": 1
			}, {
				"gameVersion": "1.17.1",
				"projectFileId": 3596659,
				"projectFileName": "Bookshelf-Fabric-1.17.1-11.0.3.jar",
				"fileType": 3,
				"gameVersionFlavor": null,
				"gameVersionTypeId": 73242,
				"modLoader": 4
			}, {
				"gameVersion": "1.17.1",
				"projectFileId": 3424692,
				"projectFileName": "Bookshelf-Forge-1.17.1-11.0.3.jar",
				"fileType": 1,
				"gameVersionFlavor": null,
				"gameVersionTypeId": 73242,
				"modLoader": 1
			}, {
				"gameVersion": "1.16.4",
				"projectFileId": 3167277,
				"projectFileName": "Bookshelf-1.16.4-9.3.25.jar",
				"fileType": 1,
				"gameVersionFlavor": null,
				"gameVersionTypeId": 70886,
				"modLoader": 1
			}, {
				"gameVersion": "1.16.4",
				"projectFileId": 3165001,
				"projectFileName": "Bookshelf-1.16.4-9.3.23.jar",
				"fileType": 3,
				"gameVersionFlavor": null,
				"gameVersionTypeId": 70886,
				"modLoader": 1
			}, {
				"gameVersion": "1.16.3",
				"projectFileId": 3090977,
				"projectFileName": "Bookshelf-1.16.3-8.7.20.jar",
				"fileType": 1,
				"gameVersionFlavor": null,
				"gameVersionTypeId": 70886,
				"modLoader": 1
			}, {
				"gameVersion": "1.16.3",
				"projectFileId": 3090373,
				"projectFileName": "Bookshelf-1.16.3-8.6.19.jar",
				"fileType": 3,
				"gameVersionFlavor": null,
				"gameVersionTypeId": 70886,
				"modLoader": 1
			}, {
				"gameVersion": "1.16.2",
				"projectFileId": 3049367,
				"projectFileName": "Bookshelf-1.16.2-7.0.11.jar",
				"fileType": 1,
				"gameVersionFlavor": null,
				"gameVersionTypeId": 70886,
				"modLoader": 1
			}, {
				"gameVersion": "1.16.2",
				"projectFileId": 3048497,
				"projectFileName": "Bookshelf-1.16.2-7.0.9.jar",
				"fileType": 3,
				"gameVersionFlavor": null,
				"gameVersionTypeId": 70886,
				"modLoader": 1
			}, {
				"gameVersion": "1.16.1",
				"projectFileId": 3033835,
				"projectFileName": "Bookshelf-1.16.1-6.3.21.jar",
				"fileType": 1,
				"gameVersionFlavor": null,
				"gameVersionTypeId": 70886,
				"modLoader": 1
			}, {
				"gameVersion": "1.16.1",
				"projectFileId": 3026438,
				"projectFileName": "Bookshelf-1.16.1-6.3.19.jar",
				"fileType": 3,
				"gameVersionFlavor": null,
				"gameVersionTypeId": 70886,
				"modLoader": 1
			}, {
				"gameVersion": "1.16.1",
				"projectFileId": 3000934,
				"projectFileName": "Bookshelf-1.16.1-6.0.2.jar",
				"fileType": 2,
				"gameVersionFlavor": null,
				"gameVersionTypeId": 70886,
				"modLoader": 1
			}, {
				"gameVersion": "1.15.2",
				"projectFileId": 2965233,
				"projectFileName": "Bookshelf-1.15.2-5.6.40.jar",
				"fileType": 1,
				"gameVersionFlavor": null,
				"gameVersionTypeId": 68722,
				"modLoader": 1
			}, {
				"gameVersion": "1.15.2",
				"projectFileId": 2965218,
				"projectFileName": "Bookshelf-1.15.2-5.6.39.jar",
				"fileType": 3,
				"gameVersionFlavor": null,
				"gameVersionTypeId": 68722,
				"modLoader": 1
			}, {
				"gameVersion": "1.14.4",
				"projectFileId": 2939801,
				"projectFileName": "Bookshelf-1.14.4-4.4.74.jar",
				"fileType": 1,
				"gameVersionFlavor": null,
				"gameVersionTypeId": 64806,
				"modLoader": 1
			}, {
				"gameVersion": "1.14.4",
				"projectFileId": 2939795,
				"projectFileName": "Bookshelf-1.14.4-4.4.73.jar",
				"fileType": 3,
				"gameVersionFlavor": null,
				"gameVersionTypeId": 64806,
				"modLoader": 1
			}, {
				"gameVersion": "1.15.2",
				"projectFileId": 2925072,
				"projectFileName": "Bookshelf-1.15.2-5.3.11.jar",
				"fileType": 2,
				"gameVersionFlavor": null,
				"gameVersionTypeId": 68722,
				"modLoader": 1
			}, {
				"gameVersion": "1.12.2",
				"projectFileId": 2836960,
				"projectFileName": "Bookshelf-1.12.2-2.3.590.jar",
				"fileType": 1,
				"gameVersionFlavor": null,
				"gameVersionTypeId": 628,
				"modLoader": 1
			}, {
				"gameVersion": "1.14.4",
				"projectFileId": 2825727,
				"projectFileName": "Bookshelf-1.14.4-4.2.59.jar",
				"fileType": 2,
				"gameVersionFlavor": null,
				"gameVersionTypeId": 64806,
				"modLoader": 1
			}, {
				"gameVersion": "1.14.4",
				"projectFileId": 2808278,
				"projectFileName": "Bookshelf-1.14.4-4.2.51.jar",
				"fileType": 3,
				"gameVersionFlavor": null,
				"gameVersionTypeId": 64806
			}, {
				"gameVersion": "1.12.2",
				"projectFileId": 2803161,
				"projectFileName": "Bookshelf-1.12.2-2.3.589.jar",
				"fileType": 3,
				"gameVersionFlavor": null,
				"gameVersionTypeId": 628,
				"modLoader": 1
			}, {
				"gameVersion": "1.12.2",
				"projectFileId": 2758684,
				"projectFileName": "Bookshelf-1.12.2-2.3.588.jar",
				"fileType": 3,
				"gameVersionFlavor": null,
				"gameVersionTypeId": 628
			}, {
				"gameVersion": "1.14.4",
				"projectFileId": 2758578,
				"projectFileName": "Bookshelf-1.14.4-4.2.35.jar",
				"fileType": 2,
				"gameVersionFlavor": null,
				"gameVersionTypeId": 64806
			}, {
				"gameVersion": "1.13.2",
				"projectFileId": 2757474,
				"projectFileName": "Bookshelf-1.13.2-3.0.20.jar",
				"fileType": 1,
				"gameVersionFlavor": null,
				"gameVersionTypeId": 55023,
				"modLoader": 1
			}, {
				"gameVersion": "1.13.2",
				"projectFileId": 2752483,
				"projectFileName": "Bookshelf-1.13.2-3.0.17.jar",
				"fileType": 3,
				"gameVersionFlavor": null,
				"gameVersionTypeId": 55023
			}, {
				"gameVersion": "1.14.3",
				"projectFileId": 2745033,
				"projectFileName": "Bookshelf-1.14.3-4.1.32.jar",
				"fileType": 3,
				"gameVersionFlavor": null,
				"gameVersionTypeId": 64806,
				"modLoader": 1
			}, {
				"gameVersion": "1.14.3",
				"projectFileId": 2743359,
				"projectFileName": "Bookshelf-1.14.3-4.1.31.jar",
				"fileType": 3,
				"gameVersionFlavor": null,
				"gameVersionTypeId": 64806
			}, {
				"gameVersion": "1.14.3",
				"projectFileId": 2738964,
				"projectFileName": "Bookshelf-1.14.3-4.1.29.jar",
				"fileType": 2,
				"gameVersionFlavor": null,
				"gameVersionTypeId": 64806
			}, {
				"gameVersion": "1.14.2",
				"projectFileId": 2729574,
				"projectFileName": "Bookshelf-1.14.2-4.0.14.jar",
				"fileType": 2,
				"gameVersionFlavor": null,
				"gameVersionTypeId": 64806,
				"modLoader": 1
			}, {
				"gameVersion": "1.14.2",
				"projectFileId": 2729554,
				"projectFileName": "Bookshelf-1.14.2-4.0.13.jar",
				"fileType": 3,
				"gameVersionFlavor": null,
				"gameVersionTypeId": 64806
			}, {
				"gameVersion": "1.12.2",
				"projectFileId": 2723580,
				"projectFileName": "Bookshelf-1.12.2-2.3.584.jar",
				"fileType": 1,
				"gameVersionFlavor": null,
				"gameVersionTypeId": 628
			}, {
				"gameVersion": "1.14.2",
				"projectFileId": 2722667,
				"projectFileName": "Bookshelf-1.14.2-4.0.2.jar",
				"fileType": 2,
				"gameVersionFlavor": null,
				"gameVersionTypeId": 64806
			}, {
				"gameVersion": "1.13.2",
				"projectFileId": 2720949,
				"projectFileName": "Bookshelf-1.13.2-3.0.8.jar",
				"fileType": 2,
				"gameVersionFlavor": null,
				"gameVersionTypeId": 55023
			}, {
				"gameVersion": "1.10.2",
				"projectFileId": 2650707,
				"projectFileName": "Bookshelf-1.10.2-1.4.4.final.1.jar",
				"fileType": 1,
				"gameVersionFlavor": null,
				"gameVersionTypeId": 572,
				"modLoader": 1
			}, {
				"gameVersion": "1.12.1",
				"projectFileId": 2481208,
				"projectFileName": "Bookshelf-1.12.1-2.1.441.jar",
				"fileType": 1,
				"gameVersionFlavor": null,
				"gameVersionTypeId": 628,
				"modLoader": 1
			}, {
				"gameVersion": "1.12",
				"projectFileId": 2481208,
				"projectFileName": "Bookshelf-1.12.1-2.1.441.jar",
				"fileType": 1,
				"gameVersionFlavor": null,
				"gameVersionTypeId": 628,
				"modLoader": 1
			}, {
				"gameVersion": "1.12.1",
				"projectFileId": 2480717,
				"projectFileName": "Bookshelf-1.12.1-2.1.440.jar",
				"fileType": 3,
				"gameVersionFlavor": null,
				"gameVersionTypeId": 628
			}, {
				"gameVersion": "1.12",
				"projectFileId": 2480717,
				"projectFileName": "Bookshelf-1.12.1-2.1.440.jar",
				"fileType": 3,
				"gameVersionFlavor": null,
				"gameVersionTypeId": 628
			}, {
				"gameVersion": "1.12.1",
				"projectFileId": 2477752,
				"projectFileName": "Bookshelf-1.12.1-2.1.436.jar",
				"fileType": 1,
				"gameVersionFlavor": null,
				"gameVersionTypeId": 628
			}, {
				"gameVersion": "1.12",
				"projectFileId": 2477752,
				"projectFileName": "Bookshelf-1.12.1-2.1.436.jar",
				"fileType": 1,
				"gameVersionFlavor": null,
				"gameVersionTypeId": 628
			}, {
				"gameVersion": "1.11.2",
				"projectFileId": 2433494,
				"projectFileName": "Bookshelf-1.11.2-2.0.0.388.jar",
				"fileType": 1,
				"gameVersionFlavor": null,
				"gameVersionTypeId": 599,
				"modLoader": 1
			}, {
				"gameVersion": "1.11.2",
				"projectFileId": 2431204,
				"projectFileName": "Bookshelf-1.11.2-2.0.0.387.jar",
				"fileType": 3,
				"gameVersionFlavor": null,
				"gameVersionTypeId": 599
			}, {
				"gameVersion": "1.11.2",
				"projectFileId": 2417989,
				"projectFileName": "Bookshelf-1.11.2-1.5.0.371.jar",
				"fileType": 1,
				"gameVersionFlavor": null,
				"gameVersionTypeId": 599
			}, {
				"gameVersion": "1.10.2",
				"projectFileId": 2398561,
				"projectFileName": "Bookshelf-1.10.2-1.4.4.346.jar",
				"fileType": 3,
				"gameVersionFlavor": null,
				"gameVersionTypeId": 572
			}, {
				"gameVersion": "1.10.2",
				"projectFileId": 2347107,
				"projectFileName": "Bookshelf-1.10.2-1.4.3.338.jar",
				"fileType": 1,
				"gameVersionFlavor": null,
				"gameVersionTypeId": 572
			}, {
				"gameVersion": "1.10",
				"projectFileId": 2310216,
				"projectFileName": "Bookshelf-1.10-1.3.0.280.jar",
				"fileType": 1,
				"gameVersionFlavor": null,
				"gameVersionTypeId": 572,
				"modLoader": 1
			}, {
				"gameVersion": "1.9.4",
				"projectFileId": 2310205,
				"projectFileName": "Bookshelf-1.9.4-1.2.3.279.jar",
				"fileType": 1,
				"gameVersionFlavor": null,
				"gameVersionTypeId": 552,
				"modLoader": 1
			}, {
				"gameVersion": "1.9.4",
				"projectFileId": 2309129,
				"projectFileName": "Bookshelf-1.9.4-1.2.3.278.jar",
				"fileType": 3,
				"gameVersionFlavor": null,
				"gameVersionTypeId": 552
			}, {
				"gameVersion": "1.9.4",
				"projectFileId": 2306544,
				"projectFileName": "Bookshelf-1.9.4-1.2.3.268.jar",
				"fileType": 1,
				"gameVersionFlavor": null,
				"gameVersionTypeId": 552
			}, {
				"gameVersion": "1.9",
				"projectFileId": 2301027,
				"projectFileName": "Bookshelf-1.9-1.2.0.243.jar",
				"fileType": 3,
				"gameVersionFlavor": null,
				"gameVersionTypeId": 552
			}, {
				"gameVersion": "1.9",
				"projectFileId": 2299826,
				"projectFileName": "Bookshelf-1.9-1.2.0.241.jar",
				"fileType": 1,
				"gameVersionFlavor": null,
				"gameVersionTypeId": 552
			}, {
				"gameVersion": "1.8.9",
				"projectFileId": 2285982,
				"projectFileName": "Bookshelf-1.8.9-1.1.2.207.jar",
				"fileType": 1,
				"gameVersionFlavor": null,
				"gameVersionTypeId": 4,
				"modLoader": 1
			}, {
				"gameVersion": "1.8.9",
				"projectFileId": 2285557,
				"projectFileName": "Bookshelf-1.8.9-1.1.2.206.jar",
				"fileType": 1,
				"gameVersionFlavor": null,
				"gameVersionTypeId": 4
			}, {
				"gameVersion": "1.8.9",
				"projectFileId": 2285393,
				"projectFileName": "Bookshelf-1.8.9-1.1.1.205.jar",
				"fileType": 2,
				"gameVersionFlavor": null,
				"gameVersionTypeId": 4
			}, {
				"gameVersion": "1.7.10",
				"projectFileId": 2278984,
				"projectFileName": "Bookshelf-1.7.10-1.0.4.187.jar",
				"fileType": 1,
				"gameVersionFlavor": null,
				"gameVersionTypeId": 5,
				"modLoader": 1
			}, {
				"gameVersion": "1.7.10",
				"projectFileId": 2274152,
				"projectFileName": "Bookshelf-1.7.10-1.0.4.178.jar",
				"fileType": 2,
				"gameVersionFlavor": null,
				"gameVersionTypeId": 5
			}, {
				"gameVersion": "1.7.10",
				"projectFileId": 2272636,
				"projectFileName": "Bookshelf-1.7.10-1.0.4.172.jar",
				"fileType": 1,
				"gameVersionFlavor": null,
				"gameVersionTypeId": 5
			}
		],
		"isFeatured": false,
		"popularityScore": 56034.74609375,
		"gamePopularityRank": 13,
		"primaryLanguage": "enUS",
		"gameSlug": "minecraft",
		"modLoaders": ["Forge"],
		"gameName": "Minecraft",
		"portalName": "www.curseforge.com",
		"dateModified": "2022-01-26T10:26:18.09Z",
		"dateCreated": "2015-03-12T02:52:59.353Z",
		"dateReleased": "2022-01-26T10:26:03.307Z",
		"isAvailable": true,
		"isExperiemental": false,
		"allowModDistribution": true
	},
	{
	"id": 452344,
	"name": "Bayou Blues (Forge)",
	"authors": [
		{
			"name": "team_aurora_modding",
			"url": "https://www.curseforge.com/members/101158216-team_aurora_modding?username=team_aurora_modding",
			"projectId": 452344,
			"id": 365015,
			"projectTitleId": 8,
			"projectTitleTitle": "Mascot",
			"userId": 101158216,
			"twitchId": 539689142
		}, {
			"name": "JustoPlayzz_",
			"url": "https://www.curseforge.com/members/101609846-justoplayzz_?username=justoplayzz_",
			"projectId": 452344,
			"id": 495434,
			"projectTitleId": 2,
			"projectTitleTitle": "Author",
			"userId": 101609846,
			"twitchId": 518268391
		}, {
			"name": "StevePlayzz_",
			"url": "https://www.curseforge.com/members/101388901-steveplayzz_?username=steveplayzz_",
			"projectId": 452344,
			"id": 495433,
			"projectTitleId": 2,
			"projectTitleTitle": "Author",
			"userId": 101388901,
			"twitchId": 571350148
		}, {
			"name": "ex0planetary",
			"url": "https://www.curseforge.com/members/47165040-ex0planetary?username=ex0planetary",
			"projectId": 452344,
			"id": 364923,
			"projectTitleId": 2,
			"projectTitleTitle": "Author",
			"userId": 47165040,
			"twitchId": 152484195
		}, {
			"name": "Shock_Micro",
			"url": "https://www.curseforge.com/members/53415868-shock_micro?username=shock_micro",
			"projectId": 452344,
			"id": 365016,
			"projectTitleId": 2,
			"projectTitleTitle": "Author",
			"userId": 53415868,
			"twitchId": 246194889
		}
	],
	"attachments": [
		{
			"id": 349912,
			"projectId": 452344,
			"description": "",
			"isDefault": true,
			"thumbnailUrl": "https://media.forgecdn.net/avatars/thumbnails/349/912/256/256/637502319924440542.png",
			"title": "637502319924440542.png",
			"url": "https://media.forgecdn.net/avatars/349/912/637502319924440542.png",
			"status": 1
		}, {
			"id": 344673,
			"projectId": 452344,
			"description": "",
			"isDefault": false,
			"thumbnailUrl": "https://media.forgecdn.net/attachments/thumbnails/344/673/310/172/2021-03-01_21.png",
			"title": "Beard Moss",
			"url": "https://media.forgecdn.net/attachments/344/673/2021-03-01_21.png",
			"status": 1
		}, {
			"id": 344671,
			"projectId": 452344,
			"description": "",
			"isDefault": false,
			"thumbnailUrl": "https://media.forgecdn.net/attachments/thumbnails/344/671/310/172/2021-03-01_21.png",
			"title": "Cypress Trees",
			"url": "https://media.forgecdn.net/attachments/344/671/2021-03-01_21.png",
			"status": 1
		}, {
			"id": 344674,
			"projectId": 452344,
			"description": "",
			"isDefault": false,
			"thumbnailUrl": "https://media.forgecdn.net/attachments/thumbnails/344/674/310/172/2021-03-01_21.png",
			"title": "Lily Flowers",
			"url": "https://media.forgecdn.net/attachments/344/674/2021-03-01_21.png",
			"status": 1
		}, {
			"id": 344672,
			"projectId": 452344,
			"description": "",
			"isDefault": false,
			"thumbnailUrl": "https://media.forgecdn.net/attachments/thumbnails/344/672/310/172/2021-03-01_21.png",
			"title": "Gooseberries",
			"url": "https://media.forgecdn.net/attachments/344/672/2021-03-01_21.png",
			"status": 1
		}, {
			"id": 344670,
			"projectId": 452344,
			"description": "House made with Bayou materials (cypress wood & algae thatch)",
			"isDefault": false,
			"thumbnailUrl": "https://media.forgecdn.net/attachments/thumbnails/344/670/310/172/2021-02-16_20.png",
			"title": "Bayou House",
			"url": "https://media.forgecdn.net/attachments/344/670/2021-02-16_20.png",
			"status": 1
		}, {
			"id": 344669,
			"projectId": 452344,
			"description": "",
			"isDefault": false,
			"thumbnailUrl": "https://media.forgecdn.net/attachments/thumbnails/344/669/310/172/2021-02-12_14.png",
			"title": "Bayou",
			"url": "https://media.forgecdn.net/attachments/344/669/2021-02-12_14.png",
			"status": 1
		}
	],
	"issueTrackerUrl": "https://github.com/teamauroramods/BayouBlues-Forge/issues",
	"wikiUrl": "https://docs.google.com/document/d/e/2PACX-1vTexG0qtaEV07dYhwysGSL5lGiA01-YHRBXtCCmkOdzNdmVs9U3SGraN27hvX0TOBD8lcsy6IQCwJts/pub",
	"sourceUrl": "https://github.com/teamauroramods/BayouBlues-Forge",
	"websiteUrl": "https://www.curseforge.com/minecraft/mc-mods/bayou-blues",
	"gameId": 432,
	"summary": "A swampy new Bayou biome!",
	"defaultFileId": 3342861,
	"downloadCount": 3764888.0,
	"latestFiles": [
		{
			"id": 3342861,
			"displayName": "Bayou-Blues-1.16.5-1.0.5.jar",
			"fileName": "Bayou-Blues-1.16.5-1.0.5.jar",
			"fileDate": "2021-06-08T00:34:26.867Z",
			"fileLength": 554081,
			"releaseType": 1,
			"fileStatus": 4,
			"downloadUrl": "https://edge.forgecdn.net/files/3342/861/Bayou-Blues-1.16.5-1.0.5.jar",
			"isAlternate": false,
			"alternateFileId": 0,
			"dependencies": [
				{
					"id": 65795975,
					"addonId": 382216,
					"type": 3,
					"fileId": 3342861
				}
			],
			"isAvailable": true,
			"modules": [
				{
					"foldername": "META-INF",
					"fingerprint": 32184325,
					"type": 3
				}, {
					"foldername": "com",
					"fingerprint": 1793073509,
					"type": 3
				}, {
					"foldername": "assets",
					"fingerprint": 2372367252,
					"type": 3
				}, {
					"foldername": "data",
					"fingerprint": 1810053333,
					"type": 3
				}, {
					"foldername": "logo.png",
					"fingerprint": 312407212,
					"type": 3
				}, {
					"foldername": "pack.mcmeta",
					"fingerprint": 1814206711,
					"type": 3
				}
			],
			"packageFingerprint": 797610327,
			"gameVersion": ["1.16.5", "Forge"],
			"sortableGameVersion": [
				{
					"gameVersionPadded": "0000000001.0000000016.0000000005",
					"gameVersion": "1.16.5",
					"gameVersionReleaseDate": "2021-01-15T14:14:48.91Z",
					"gameVersionName": "1.16.5",
					"gameVersionTypeId": 70886
				}, {
					"gameVersionPadded": "0",
					"gameVersion": "",
					"gameVersionReleaseDate": "2019-08-01T00:00:00Z",
					"gameVersionName": "Forge",
					"gameVersionTypeId": 68441
				}
			],
			"installMetadata": null,
			"changelog": null,
			"hasInstallScript": false,
			"isCompatibleWithClient": true,
			"categorySectionPackageType": 6,
			"restrictProjectFileAccess": 1,
			"projectStatus": 4,
			"renderCacheId": 2351167,
			"fileLegacyMappingId": null,
			"projectId": 452344,
			"parentProjectFileId": null,
			"parentFileLegacyMappingId": null,
			"fileTypeId": null,
			"exposeAsAlternative": null,
			"packageFingerprintId": 678595547,
			"gameVersionDateReleased": "2019-08-01T00:00:00Z",
			"gameVersionMappingId": 3019199,
			"gameVersionId": 7498,
			"gameId": 432,
			"isServerPack": false,
			"serverPackFileId": null,
			"gameVersionFlavor": null,
			"hashes": [
				{
					"algorithm": 1,
					"value": "5ac5559f0d267a104131609f837db89ea03774fa"
				}, {
					"algorithm": 2,
					"value": "7cfbc440029484934ca0734052716e83"
				}
			],
			"downloadCount": 2735018
		}
	],
	"categories": [
		{
			"categoryId": 436,
			"name": "Food",
			"url": "https://www.curseforge.com/minecraft/mc-mods/mc-food",
			"avatarUrl": "https://media.forgecdn.net/avatars/6/49/635351499265510402.png",
			"parentId": 6,
			"rootId": 6,
			"projectId": 452344,
			"avatarId": 6049,
			"gameId": 432,
			"slug": "mc-food",
			"dateModified": "2014-05-08T17:45:26.55Z"
		}, {
			"categoryId": 407,
			"name": "Biomes",
			"url": "https://www.curseforge.com/minecraft/mc-mods/world-gen/world-biomes",
			"avatarUrl": "https://media.forgecdn.net/avatars/6/22/635351492995856506.png",
			"parentId": 406,
			"rootId": 6,
			"projectId": 452344,
			"avatarId": 6022,
			"gameId": 432,
			"slug": "world-biomes",
			"dateModified": "2014-05-08T17:34:59.587Z"
		}
	],
	"status": 4,
	"primaryCategoryId": 5129,
	"categorySection": {
		"id": 8,
		"gameId": 432,
		"name": "Mods",
		"packageType": 6,
		"path": "mods",
		"initialInclusionPattern": ".",
		"extraIncludePattern": null,
		"gameCategoryId": 6
	},
	"slug": "bayou-blues",
	"gameVersionLatestFiles": [
		{
			"gameVersion": "1.16.5",
			"projectFileId": 3342861,
			"projectFileName": "Bayou-Blues-1.16.5-1.0.5.jar",
			"fileType": 1,
			"gameVersionFlavor": null,
			"gameVersionTypeId": 70886,
			"modLoader": 1
		}, {
			"gameVersion": "1.16.4",
			"projectFileId": 3250109,
			"projectFileName": "Bayou-Blues-1.16.5-1.0.4.jar",
			"fileType": 1,
			"gameVersionFlavor": null,
			"gameVersionTypeId": 70886,
			"modLoader": 1
		}
	],
	"isFeatured": false,
	"popularityScore": 9354.115234375,
	"gamePopularityRank": 570,
	"primaryLanguage": "enUS",
	"gameSlug": "minecraft",
	"modLoaders": ["Forge"],
	"gameName": "Minecraft",
	"portalName": "www.curseforge.com",
	"dateModified": "2022-01-25T22:27:01.437Z",
	"dateCreated": "2021-03-01T21:46:32.43Z",
	"dateReleased": "2021-06-08T00:34:26.867Z",
	"isAvailable": true,
	"isExperiemental": false,
	"allowModDistribution": true
},
	{
	"id": 238222,
	"name": "Just Enough Items (JEI)",
	"authors": [
		{
			"name": "mezz",
			"url": "https://www.curseforge.com/members/17072262-mezz?username=mezz",
			"projectId": 238222,
			"id": 32358,
			"projectTitleId": null,
			"projectTitleTitle": null,
			"userId": 17072262,
			"twitchId": 56761389
		}
	],
	"attachments": [
		{
			"id": 29069,
			"projectId": 238222,
			"description": "",
			"isDefault": true,
			"thumbnailUrl": "https://media.forgecdn.net/avatars/thumbnails/29/69/256/256/635838945588716414.jpeg",
			"title": "635838945588716414.jpeg",
			"url": "https://media.forgecdn.net/avatars/29/69/635838945588716414.jpeg",
			"status": 1
		}, {
			"id": 31417,
			"projectId": 238222,
			"description": "",
			"isDefault": false,
			"thumbnailUrl": "https://media.forgecdn.net/attachments/thumbnails/31/417/310/172/thzzdin.png",
			"title": "Recipe Completion",
			"url": "https://media.forgecdn.net/attachments/31/417/thzzdin.png",
			"status": 1
		}, {
			"id": 31419,
			"projectId": 238222,
			"description": "",
			"isDefault": false,
			"thumbnailUrl": "https://media.forgecdn.net/attachments/thumbnails/31/419/310/172/t7f7jh6.png",
			"title": "Potions",
			"url": "https://media.forgecdn.net/attachments/31/419/t7f7jh6.png",
			"status": 1
		}, {
			"id": 31420,
			"projectId": 238222,
			"description": "",
			"isDefault": false,
			"thumbnailUrl": "https://media.forgecdn.net/attachments/thumbnails/31/420/310/172/tgafkma.png",
			"title": "Itemlist Edit Mode",
			"url": "https://media.forgecdn.net/attachments/31/420/tgafkma.png",
			"status": 1
		}, {
			"id": 31418,
			"projectId": 238222,
			"description": "",
			"isDefault": false,
			"thumbnailUrl": "https://media.forgecdn.net/attachments/thumbnails/31/418/310/172/9lngh5f.png",
			"title": "Big Screen Support",
			"url": "https://media.forgecdn.net/attachments/31/418/9lngh5f.png",
			"status": 1
		}
	],
	"issueTrackerUrl": "https://github.com/mezz/JustEnoughItems/issues?q=is%3Aissue",
	"wikiUrl": "",
	"sourceUrl": "https://github.com/mezz/JustEnoughItems",
	"websiteUrl": "https://www.curseforge.com/minecraft/mc-mods/jei",
	"gameId": 432,
	"summary": "View Items and Recipes",
	"defaultFileId": 3599262,
	"downloadCount": 150768835.0,
	"latestFiles": [
		{
			"id": 3040523,
			"displayName": "jei_1.12.2-4.16.1.301.jar",
			"fileName": "jei_1.12.2-4.16.1.301.jar",
			"fileDate": "2020-08-24T01:01:39.123Z",
			"fileLength": 653211,
			"releaseType": 1,
			"fileStatus": 4,
			"downloadUrl": "https://edge.forgecdn.net/files/3040/523/jei_1.12.2-4.16.1.301.jar",
			"isAlternate": false,
			"alternateFileId": 0,
			"dependencies": [],
			"isAvailable": true,
			"modules": [
				{
					"foldername": "META-INF",
					"fingerprint": 2236405288,
					"type": 3
				}, {
					"foldername": "mezz",
					"fingerprint": 2222830911,
					"type": 3
				}, {
					"foldername": "pack.mcmeta",
					"fingerprint": 1488642189,
					"type": 3
				}, {
					"foldername": "mcmod.info",
					"fingerprint": 3528499262,
					"type": 3
				}, {
					"foldername": "assets",
					"fingerprint": 9943101,
					"type": 3
				}
			],
			"packageFingerprint": 3089143260,
			"gameVersion": ["1.12.2"],
			"sortableGameVersion": [
				{
					"gameVersionPadded": "0000000001.0000000012.0000000002",
					"gameVersion": "1.12.2",
					"gameVersionReleaseDate": "2017-09-18T05:00:00Z",
					"gameVersionName": "1.12.2",
					"gameVersionTypeId": 628
				}
			],
			"installMetadata": null,
			"changelog": null,
			"hasInstallScript": false,
			"isCompatibleWithClient": true,
			"categorySectionPackageType": 6,
			"restrictProjectFileAccess": 1,
			"projectStatus": 4,
			"renderCacheId": 1967311,
			"fileLegacyMappingId": null,
			"projectId": 238222,
			"parentProjectFileId": null,
			"parentFileLegacyMappingId": null,
			"fileTypeId": null,
			"exposeAsAlternative": null,
			"packageFingerprintId": 510670740,
			"gameVersionDateReleased": "2008-03-01T06:00:00Z",
			"gameVersionMappingId": 2394328,
			"gameVersionId": 4458,
			"gameId": 432,
			"isServerPack": false,
			"serverPackFileId": null,
			"gameVersionFlavor": null,
			"hashes": [
				{
					"algorithm": 1,
					"value": "3045e8440ea44071d8b83c4e7b3c190348fdc527"
				}, {
					"algorithm": 2,
					"value": "1dee4be93d666e2228039c551e927b35"
				}
			],
			"downloadCount": 11681196
		}, {
			"id": 3043174,
			"displayName": "jei_1.12.2-4.16.1.302.jar",
			"fileName": "jei_1.12.2-4.16.1.302.jar",
			"fileDate": "2020-08-27T01:47:46.263Z",
			"fileLength": 653210,
			"releaseType": 2,
			"fileStatus": 4,
			"downloadUrl": "https://edge.forgecdn.net/files/3043/174/jei_1.12.2-4.16.1.302.jar",
			"isAlternate": false,
			"alternateFileId": 0,
			"dependencies": [],
			"isAvailable": true,
			"modules": [
				{
					"foldername": "META-INF",
					"fingerprint": 457918307,
					"type": 3
				}, {
					"foldername": "mezz",
					"fingerprint": 2799571216,
					"type": 3
				}, {
					"foldername": "pack.mcmeta",
					"fingerprint": 1488642189,
					"type": 3
				}, {
					"foldername": "mcmod.info",
					"fingerprint": 3001924313,
					"type": 3
				}, {
					"foldername": "assets",
					"fingerprint": 9943101,
					"type": 3
				}
			],
			"packageFingerprint": 1065578237,
			"gameVersion": ["1.12.2"],
			"sortableGameVersion": [
				{
					"gameVersionPadded": "0000000001.0000000012.0000000002",
					"gameVersion": "1.12.2",
					"gameVersionReleaseDate": "2017-09-18T05:00:00Z",
					"gameVersionName": "1.12.2",
					"gameVersionTypeId": 628
				}
			],
			"installMetadata": null,
			"changelog": null,
			"hasInstallScript": false,
			"isCompatibleWithClient": true,
			"categorySectionPackageType": 6,
			"restrictProjectFileAccess": 1,
			"projectStatus": 4,
			"renderCacheId": 1970605,
			"fileLegacyMappingId": null,
			"projectId": 238222,
			"parentProjectFileId": null,
			"parentFileLegacyMappingId": null,
			"fileTypeId": null,
			"exposeAsAlternative": null,
			"packageFingerprintId": 512127697,
			"gameVersionDateReleased": "2008-03-01T06:00:00Z",
			"gameVersionMappingId": 2399976,
			"gameVersionId": 4458,
			"gameId": 432,
			"isServerPack": false,
			"serverPackFileId": null,
			"gameVersionFlavor": null,
			"hashes": [
				{
					"algorithm": 1,
					"value": "3e88d2896ca868c3cedb65e117ad3a1b82488fa8"
				}, {
					"algorithm": 2,
					"value": "2dc4b6046812e64c514ff4d18bc5cb03"
				}
			],
			"downloadCount": 6688692
		}, {
			"id": 3071356,
			"displayName": "jei-1.16.3-7.4.0.40.jar",
			"fileName": "jei-1.16.3-7.4.0.40.jar",
			"fileDate": "2020-10-04T02:12:05.583Z",
			"fileLength": 757768,
			"releaseType": 3,
			"fileStatus": 4,
			"downloadUrl": "https://edge.forgecdn.net/files/3071/356/jei-1.16.3-7.4.0.40.jar",
			"isAlternate": false,
			"alternateFileId": 0,
			"dependencies": [],
			"isAvailable": true,
			"modules": [
				{
					"foldername": "META-INF",
					"fingerprint": 3364756391,
					"type": 3
				}, {
					"foldername": "mezz",
					"fingerprint": 271191008,
					"type": 3
				}, {
					"foldername": "pack.mcmeta",
					"fingerprint": 1645019714,
					"type": 3
				}, {
					"foldername": "assets",
					"fingerprint": 3480510006,
					"type": 3
				}
			],
			"packageFingerprint": 2915111560,
			"gameVersion": ["1.16.3", "Forge"],
			"sortableGameVersion": [
				{
					"gameVersionPadded": "0000000001.0000000016.0000000003",
					"gameVersion": "1.16.3",
					"gameVersionReleaseDate": "2020-09-10T14:44:20.443Z",
					"gameVersionName": "1.16.3",
					"gameVersionTypeId": 70886
				}, {
					"gameVersionPadded": "0",
					"gameVersion": "",
					"gameVersionReleaseDate": "2019-08-01T00:00:00Z",
					"gameVersionName": "Forge",
					"gameVersionTypeId": 68441
				}
			],
			"installMetadata": null,
			"changelog": null,
			"hasInstallScript": false,
			"isCompatibleWithClient": true,
			"categorySectionPackageType": 6,
			"restrictProjectFileAccess": 1,
			"projectStatus": 4,
			"renderCacheId": 2005111,
			"fileLegacyMappingId": null,
			"projectId": 238222,
			"parentProjectFileId": null,
			"parentFileLegacyMappingId": null,
			"fileTypeId": null,
			"exposeAsAlternative": null,
			"packageFingerprintId": 530292265,
			"gameVersionDateReleased": "2008-03-01T06:00:00Z",
			"gameVersionMappingId": 2458314,
			"gameVersionId": 4458,
			"gameId": 432,
			"isServerPack": false,
			"serverPackFileId": null,
			"gameVersionFlavor": null,
			"hashes": [
				{
					"algorithm": 1,
					"value": "628a92cfe4cb4d4c45d18548375910cabd37a9b7"
				}, {
					"algorithm": 2,
					"value": "791efe9fe882b9ff4d48153dfec4308d"
				}
			],
			"downloadCount": 75777
		}, {
			"id": 3272039,
			"displayName": "jei-1.13.2-5.0.0.31.jar",
			"fileName": "jei-1.13.2-5.0.0.31.jar",
			"fileDate": "2021-04-11T03:49:47.687Z",
			"fileLength": 690802,
			"releaseType": 3,
			"fileStatus": 4,
			"downloadUrl": "https://edge.forgecdn.net/files/3272/39/jei-1.13.2-5.0.0.31.jar",
			"isAlternate": false,
			"alternateFileId": 0,
			"dependencies": [],
			"isAvailable": true,
			"modules": [
				{
					"foldername": "META-INF",
					"fingerprint": 1102858494,
					"type": 3
				}, {
					"foldername": "mezz",
					"fingerprint": 2811918946,
					"type": 3
				}, {
					"foldername": "pack.mcmeta",
					"fingerprint": 3652707984,
					"type": 3
				}, {
					"foldername": "assets",
					"fingerprint": 88833534,
					"type": 3
				}
			],
			"packageFingerprint": 2700304635,
			"gameVersion": ["1.13.2"],
			"sortableGameVersion": [
				{
					"gameVersionPadded": "0000000001.0000000013.0000000002",
					"gameVersion": "1.13.2",
					"gameVersionReleaseDate": "2018-10-22T00:00:00Z",
					"gameVersionName": "1.13.2",
					"gameVersionTypeId": 55023
				}
			],
			"installMetadata": null,
			"changelog": null,
			"hasInstallScript": false,
			"isCompatibleWithClient": true,
			"categorySectionPackageType": 6,
			"restrictProjectFileAccess": 1,
			"projectStatus": 4,
			"renderCacheId": 2260348,
			"fileLegacyMappingId": null,
			"projectId": 238222,
			"parentProjectFileId": null,
			"parentFileLegacyMappingId": null,
			"fileTypeId": null,
			"exposeAsAlternative": null,
			"packageFingerprintId": 641872978,
			"gameVersionDateReleased": "2008-03-01T06:00:00Z",
			"gameVersionMappingId": 2857385,
			"gameVersionId": 4458,
			"gameId": 432,
			"isServerPack": false,
			"serverPackFileId": null,
			"gameVersionFlavor": null,
			"hashes": [
				{
					"algorithm": 1,
					"value": "aa15cdea079db8b91d75e3c68216df80a70545d8"
				}, {
					"algorithm": 2,
					"value": "1ee1f4fb4c6e199c02c7d15cbd0d2c8a"
				}
			],
			"downloadCount": 8508
		}, {
			"id": 3599262,
			"displayName": "jei-1.18.1-9.2.1.69.jar",
			"fileName": "jei-1.18.1-9.2.1.69.jar",
			"fileDate": "2022-01-09T03:05:05.7Z",
			"fileLength": 837745,
			"releaseType": 1,
			"fileStatus": 4,
			"downloadUrl": "https://edge.forgecdn.net/files/3599/262/jei-1.18.1-9.2.1.69.jar",
			"isAlternate": false,
			"alternateFileId": 0,
			"dependencies": [],
			"isAvailable": true,
			"modules": [
				{
					"foldername": "META-INF",
					"fingerprint": 3760951589,
					"type": 3
				}, {
					"foldername": "mezz",
					"fingerprint": 3018598536,
					"type": 3
				}, {
					"foldername": "pack.mcmeta",
					"fingerprint": 910812358,
					"type": 3
				}, {
					"foldername": "assets",
					"fingerprint": 2666385551,
					"type": 3
				}
			],
			"packageFingerprint": 2681456912,
			"gameVersion": ["1.18.1", "Forge"],
			"sortableGameVersion": [
				{
					"gameVersionPadded": "0000000001.0000000018.0000000001",
					"gameVersion": "1.18.1",
					"gameVersionReleaseDate": "2021-12-10T10:37:38.06Z",
					"gameVersionName": "1.18.1",
					"gameVersionTypeId": 73250
				}, {
					"gameVersionPadded": "0",
					"gameVersion": "",
					"gameVersionReleaseDate": "2019-08-01T00:00:00Z",
					"gameVersionName": "Forge",
					"gameVersionTypeId": 68441
				}
			],
			"installMetadata": null,
			"changelog": null,
			"hasInstallScript": false,
			"isCompatibleWithClient": true,
			"categorySectionPackageType": 6,
			"restrictProjectFileAccess": 1,
			"projectStatus": 4,
			"renderCacheId": 2673216,
			"fileLegacyMappingId": null,
			"projectId": 238222,
			"parentProjectFileId": null,
			"parentFileLegacyMappingId": null,
			"fileTypeId": null,
			"exposeAsAlternative": null,
			"packageFingerprintId": 829861699,
			"gameVersionDateReleased": "2019-08-01T00:00:00Z",
			"gameVersionMappingId": 3653993,
			"gameVersionId": 7498,
			"gameId": 432,
			"isServerPack": false,
			"serverPackFileId": null,
			"gameVersionFlavor": null,
			"hashes": [
				{
					"algorithm": 1,
					"value": "f71d31072b1fc184885948872da2f2088aaf40ca"
				}, {
					"algorithm": 2,
					"value": "ec880bb557174f71c5e95100b4094055"
				}
			],
			"downloadCount": 281277
		}, {
			"id": 3622553,
			"displayName": "jei-1.18.1-9.2.3.82.jar",
			"fileName": "jei-1.18.1-9.2.3.82.jar",
			"fileDate": "2022-01-24T23:50:56.21Z",
			"fileLength": 845750,
			"releaseType": 2,
			"fileStatus": 4,
			"downloadUrl": "https://edge.forgecdn.net/files/3622/553/jei-1.18.1-9.2.3.82.jar",
			"isAlternate": false,
			"alternateFileId": 0,
			"dependencies": [],
			"isAvailable": true,
			"modules": [
				{
					"foldername": "META-INF",
					"fingerprint": 2730455310,
					"type": 3
				}, {
					"foldername": "mezz",
					"fingerprint": 2678955112,
					"type": 3
				}, {
					"foldername": "pack.mcmeta",
					"fingerprint": 1496928410,
					"type": 3
				}, {
					"foldername": "assets",
					"fingerprint": 2666385551,
					"type": 3
				}
			],
			"packageFingerprint": 3373607818,
			"gameVersion": ["1.18.1", "Forge"],
			"sortableGameVersion": [
				{
					"gameVersionPadded": "0000000001.0000000018.0000000001",
					"gameVersion": "1.18.1",
					"gameVersionReleaseDate": "2021-12-10T10:37:38.06Z",
					"gameVersionName": "1.18.1",
					"gameVersionTypeId": 73250
				}, {
					"gameVersionPadded": "0",
					"gameVersion": "",
					"gameVersionReleaseDate": "2019-08-01T00:00:00Z",
					"gameVersionName": "Forge",
					"gameVersionTypeId": 68441
				}
			],
			"installMetadata": null,
			"changelog": null,
			"hasInstallScript": false,
			"isCompatibleWithClient": true,
			"categorySectionPackageType": 6,
			"restrictProjectFileAccess": 1,
			"projectStatus": 4,
			"renderCacheId": 2702621,
			"fileLegacyMappingId": null,
			"projectId": 238222,
			"parentProjectFileId": null,
			"parentFileLegacyMappingId": null,
			"fileTypeId": null,
			"exposeAsAlternative": null,
			"packageFingerprintId": 843737502,
			"gameVersionDateReleased": "2019-08-01T00:00:00Z",
			"gameVersionMappingId": 3711012,
			"gameVersionId": 7498,
			"gameId": 432,
			"isServerPack": false,
			"serverPackFileId": null,
			"gameVersionFlavor": null,
			"hashes": [
				{
					"algorithm": 1,
					"value": "a34269aafd25491da39adb54b3f34c68dfa8f438"
				}, {
					"algorithm": 2,
					"value": "ad02137b797bb7d7b7907849c389463e"
				}
			],
			"downloadCount": 9043
		}
	],
	"categories": [
		{
			"categoryId": 423,
			"name": "Map and Information",
			"url": "https://www.curseforge.com/minecraft/mc-mods/map-information",
			"avatarUrl": "https://media.forgecdn.net/avatars/6/38/635351497437388438.png",
			"parentId": 6,
			"rootId": 6,
			"projectId": 238222,
			"avatarId": 6038,
			"gameId": 432,
			"slug": "map-information",
			"dateModified": "2014-05-08T17:42:23.74Z"
		}, {
			"categoryId": 421,
			"name": "API and Library",
			"url": "https://www.curseforge.com/minecraft/mc-mods/library-api",
			"avatarUrl": "https://media.forgecdn.net/avatars/6/36/635351496947765531.png",
			"parentId": 6,
			"rootId": 6,
			"projectId": 238222,
			"avatarId": 6036,
			"gameId": 432,
			"slug": "library-api",
			"dateModified": "2014-05-23T03:21:44.06Z"
		}
	],
	"status": 4,
	"primaryCategoryId": 423,
	"categorySection": {
		"id": 8,
		"gameId": 432,
		"name": "Mods",
		"packageType": 6,
		"path": "mods",
		"initialInclusionPattern": ".",
		"extraIncludePattern": null,
		"gameCategoryId": 6
	},
	"slug": "jei",
	"gameVersionLatestFiles": [
		{
			"gameVersion": "1.18.1",
			"projectFileId": 3622553,
			"projectFileName": "jei-1.18.1-9.2.3.82.jar",
			"fileType": 2,
			"gameVersionFlavor": null,
			"gameVersionTypeId": 73250,
			"modLoader": 1
		}, {
			"gameVersion": "1.16.5",
			"projectFileId": 3607578,
			"projectFileName": "jei-1.16.5-7.7.1.145.jar",
			"fileType": 2,
			"gameVersionFlavor": null,
			"gameVersionTypeId": 70886,
			"modLoader": 1
		}, {
			"gameVersion": "1.18.1",
			"projectFileId": 3599262,
			"projectFileName": "jei-1.18.1-9.2.1.69.jar",
			"fileType": 1,
			"gameVersionFlavor": null,
			"gameVersionTypeId": 73250,
			"modLoader": 1
		}, {
			"gameVersion": "1.17.1",
			"projectFileId": 3596034,
			"projectFileName": "jei-1.17.1-8.3.1.62.jar",
			"fileType": 2,
			"gameVersionFlavor": null,
			"gameVersionTypeId": 73242,
			"modLoader": 1
		}, {
			"gameVersion": "1.18",
			"projectFileId": 3550020,
			"projectFileName": "jei-1.18-9.0.0.40.jar",
			"fileType": 2,
			"gameVersionFlavor": null,
			"gameVersionTypeId": 73250,
			"modLoader": 1
		}, {
			"gameVersion": "1.13.2",
			"projectFileId": 3272039,
			"projectFileName": "jei-1.13.2-5.0.0.31.jar",
			"fileType": 3,
			"gameVersionFlavor": null,
			"gameVersionTypeId": 55023
		}, {
			"gameVersion": "1.15.2",
			"projectFileId": 3272032,
			"projectFileName": "jei-1.15.2-6.0.3.16.jar",
			"fileType": 3,
			"gameVersionFlavor": null,
			"gameVersionTypeId": 68722
		}, {
			"gameVersion": "1.16.4",
			"projectFileId": 3245003,
			"projectFileName": "jei-1.16.4-7.6.1.74.jar",
			"fileType": 2,
			"gameVersionFlavor": null,
			"gameVersionTypeId": 70886,
			"modLoader": 1
		}, {
			"gameVersion": "1.16.3",
			"projectFileId": 3104018,
			"projectFileName": "jei-1.16.3-7.6.0.51.jar",
			"fileType": 2,
			"gameVersionFlavor": null,
			"gameVersionTypeId": 70886,
			"modLoader": 1
		}, {
			"gameVersion": "1.16.3",
			"projectFileId": 3071356,
			"projectFileName": "jei-1.16.3-7.4.0.40.jar",
			"fileType": 3,
			"gameVersionFlavor": null,
			"gameVersionTypeId": 70886,
			"modLoader": 1
		}, {
			"gameVersion": "1.16.2",
			"projectFileId": 3060935,
			"projectFileName": "jei-1.16.2-7.3.2.28.jar",
			"fileType": 3,
			"gameVersionFlavor": null,
			"gameVersionTypeId": 70886,
			"modLoader": 1
		}, {
			"gameVersion": "1.12.2",
			"projectFileId": 3043174,
			"projectFileName": "jei_1.12.2-4.16.1.302.jar",
			"fileType": 2,
			"gameVersionFlavor": null,
			"gameVersionTypeId": 628
		}, {
			"gameVersion": "1.12.2",
			"projectFileId": 3040523,
			"projectFileName": "jei_1.12.2-4.16.1.301.jar",
			"fileType": 1,
			"gameVersionFlavor": null,
			"gameVersionTypeId": 628
		}, {
			"gameVersion": "1.14.4",
			"projectFileId": 3039707,
			"projectFileName": "jei-1.14.4-6.0.1.30.jar",
			"fileType": 3,
			"gameVersionFlavor": null,
			"gameVersionTypeId": 64806
		}, {
			"gameVersion": "1.16.1",
			"projectFileId": 3028697,
			"projectFileName": "jei-1.16.1-7.0.1.10.jar",
			"fileType": 3,
			"gameVersionFlavor": null,
			"gameVersionTypeId": 70886,
			"modLoader": 1
		}, {
			"gameVersion": "1.15.1",
			"projectFileId": 2855456,
			"projectFileName": "jei-1.15.1-6.0.0.1.jar",
			"fileType": 3,
			"gameVersionFlavor": null,
			"gameVersionTypeId": 68722
		}, {
			"gameVersion": "1.14.3",
			"projectFileId": 2738328,
			"projectFileName": "jei-1.14.3-6.0.0.8.jar",
			"fileType": 3,
			"gameVersionFlavor": null,
			"gameVersionTypeId": 64806
		}, {
			"gameVersion": "1.14.2",
			"projectFileId": 2733474,
			"projectFileName": "jei-1.14.2-6.0.0.3.jar",
			"fileType": 3,
			"gameVersionFlavor": null,
			"gameVersionTypeId": 64806
		}, {
			"gameVersion": "1.10.2",
			"projectFileId": 2561516,
			"projectFileName": "jei_1.10.2-3.14.8.422.jar",
			"fileType": 2,
			"gameVersionFlavor": null,
			"gameVersionTypeId": 572
		}, {
			"gameVersion": "1.12.1",
			"projectFileId": 2485363,
			"projectFileName": "jei_1.12.2-4.7.11.102.jar",
			"fileType": 2,
			"gameVersionFlavor": null,
			"gameVersionTypeId": 628
		}, {
			"gameVersion": "1.12",
			"projectFileId": 2485363,
			"projectFileName": "jei_1.12.2-4.7.11.102.jar",
			"fileType": 2,
			"gameVersionFlavor": null,
			"gameVersionTypeId": 628
		}, {
			"gameVersion": "1.12.1",
			"projectFileId": 2478647,
			"projectFileName": "jei_1.12.1-4.7.8.95.jar",
			"fileType": 1,
			"gameVersionFlavor": null,
			"gameVersionTypeId": 628
		}, {
			"gameVersion": "1.12",
			"projectFileId": 2478647,
			"projectFileName": "jei_1.12.1-4.7.8.95.jar",
			"fileType": 1,
			"gameVersionFlavor": null,
			"gameVersionTypeId": 628
		}, {
			"gameVersion": "1.11.2",
			"projectFileId": 2461378,
			"projectFileName": "jei_1.11.2-4.5.1.296.jar",
			"fileType": 2,
			"gameVersionFlavor": null,
			"gameVersionTypeId": 599
		}, {
			"gameVersion": "1.11.2",
			"projectFileId": 2453428,
			"projectFileName": "jei_1.11.2-4.5.0.294.jar",
			"fileType": 1,
			"gameVersionFlavor": null,
			"gameVersionTypeId": 599
		}, {
			"gameVersion": "1.12",
			"projectFileId": 2442204,
			"projectFileName": "jei_1.12-4.7.0.68.jar",
			"fileType": 3,
			"gameVersionFlavor": null,
			"gameVersionTypeId": 628
		}, {
			"gameVersion": "1.8.9",
			"projectFileId": 2431977,
			"projectFileName": "jei_1.8.9-2.28.18.187.jar",
			"fileType": 1,
			"gameVersionFlavor": null,
			"gameVersionTypeId": 4
		}, {
			"gameVersion": "1.10.2",
			"projectFileId": 2428966,
			"projectFileName": "jei_1.10.2-3.14.7.420.jar",
			"fileType": 1,
			"gameVersionFlavor": null,
			"gameVersionTypeId": 572
		}, {
			"gameVersion": "1.11",
			"projectFileId": 2360492,
			"projectFileName": "jei_1.11-4.1.1.208.jar",
			"fileType": 2,
			"gameVersionFlavor": null,
			"gameVersionTypeId": 599
		}, {
			"gameVersion": "1.11",
			"projectFileId": 2350616,
			"projectFileName": "jei_1.11-4.0.4.199.jar",
			"fileType": 3,
			"gameVersionFlavor": null,
			"gameVersionTypeId": 599
		}, {
			"gameVersion": "1.9.4",
			"projectFileId": 2313650,
			"projectFileName": "jei_1.9.4-3.6.8.225.jar",
			"fileType": 1,
			"gameVersionFlavor": null,
			"gameVersionTypeId": 552
		}, {
			"gameVersion": "1.10",
			"projectFileId": 2310912,
			"projectFileName": "jei_1.10-3.7.1.219.jar",
			"fileType": 1,
			"gameVersionFlavor": null,
			"gameVersionTypeId": 572
		}, {
			"gameVersion": "1.9.4",
			"projectFileId": 2306298,
			"projectFileName": "jei_1.9.4-3.6.2.211.jar",
			"fileType": 2,
			"gameVersionFlavor": null,
			"gameVersionTypeId": 552
		}, {
			"gameVersion": "1.9",
			"projectFileId": 2305823,
			"projectFileName": "jei_1.9.4-3.4.4.208.jar",
			"fileType": 2,
			"gameVersionFlavor": null,
			"gameVersionTypeId": 552
		}, {
			"gameVersion": "1.9",
			"projectFileId": 2304545,
			"projectFileName": "jei_1.9.4-3.4.3.207.jar",
			"fileType": 1,
			"gameVersionFlavor": null,
			"gameVersionTypeId": 552
		}, {
			"gameVersion": "1.8.9",
			"projectFileId": 2292565,
			"projectFileName": "jei_1.8.9-2.28.14.182.jar",
			"fileType": 2,
			"gameVersionFlavor": null,
			"gameVersionTypeId": 4
		}, {
			"gameVersion": "1.8.8",
			"projectFileId": 2275072,
			"projectFileName": "jei_1.8.9-2.16.2.78.jar",
			"fileType": 1,
			"gameVersionFlavor": null,
			"gameVersionTypeId": 4
		}, {
			"gameVersion": "1.8",
			"projectFileId": 2273901,
			"projectFileName": "jei_1.8-2.14.0.139.jar",
			"fileType": 1,
			"gameVersionFlavor": null,
			"gameVersionTypeId": 4
		}, {
			"gameVersion": "1.8.8",
			"projectFileId": 2270928,
			"projectFileName": "jei_1.8.8-2.8.3.39.jar",
			"fileType": 2,
			"gameVersionFlavor": null,
			"gameVersionTypeId": 4
		}, {
			"gameVersion": "1.8",
			"projectFileId": 2270927,
			"projectFileName": "jei_1.8-1.8.3.96.jar",
			"fileType": 2,
			"gameVersionFlavor": null,
			"gameVersionTypeId": 4
		}
	],
	"isFeatured": false,
	"popularityScore": 132025.53125,
	"gamePopularityRank": 1,
	"primaryLanguage": "enUS",
	"gameSlug": "minecraft",
	"modLoaders": ["Forge"],
	"gameName": "Minecraft",
	"portalName": "www.curseforge.com",
	"dateModified": "2022-01-26T02:14:40.157Z",
	"dateCreated": "2015-11-23T22:55:58.84Z",
	"dateReleased": "2022-01-24T23:50:56.21Z",
	"isAvailable": true,
	"isExperiemental": false,
	"allowModDistribution": true
}
]